topdesk_mcp/__init__.py
topdesk_mcp/_incident.py
topdesk_mcp/_operator.py
topdesk_mcp/_person.py
topdesk_mcp/_topdesk_sdk.py
topdesk_mcp/_utils.py
topdesk_mcp/main.py
topdesk_mcp/resources/fiql_query_howto.md
topdesk_mcp/resources/object_schemas.yaml
topdesk_mcp/tests/__init__.py
topdesk_mcp/tests/test_python_sdk.py
topdesk_mcp/tests/test_utils.py
topdesk_mcp-0.8.0.dist-info/METADATA
topdesk_mcp-0.8.0.dist-info/WHEEL
topdesk_mcp-0.8.0.dist-info/entry_points.txt
topdesk_mcp-0.8.0.dist-info/licenses/LICENSE
topdesk_mcp-0.8.0.dist-info/RECORD
